{
	"HardwareInfo": [
		{
			"ESModelName": {
				"string": "f0780dffeed6b140eadb44c141466523973ad03b"
			},
			"ESModelID": {
				"string": "025A"
			},
			"ESKind": {
				"int": "21"
			},
			"ESConnectionType": {
				"int": "2"
			},
			"ESProtocol": {
				"int": "1"
			},
			"ESIPv6": {
				"int": "1"
			},
			"ESBitDepth": {
				"int": "3"
			},
			"ESCommandType": {
				"int": "4"
			},
			"ESCommandTypeFlatbedOption": {
				"int": "0"
			},
			"ESInterrupt": {
				"int": "1"
			},
			"ESFlatbedType": {
				"int": "0"
			},
			"ESFlatbedOffset": {
				"int": "0"
			},
			"ESLandscapeDirection": {
				"int": "0"
			},
			"ESReduceBrightness": {
				"int": "0"
			},
			"ESADFOffset": {
				"int": "3"
			},
			"ESADFWidthMin": {
				"int": "2100"
			},
			"ESADFHeightMin": {
				"int": "2790"
			},
			"ESADFHeightMax": {
				"int": "3556"
			},
			"ESADFPreview": {
				"int": "1"
			},
			"ESHolderRange": {
				"int": "0"
			},
			"ESFilmSizeRange": {
				"int": "0"
			},
			"ESFilmSize": {
				"int": "0"
			},
			"ESTPU2Bit": {
				"int": "0"
			},
			"ESDocumentMode": {
				"int": "1"
			},
			"ESPhotoMode": {
				"int": "1"
			},
			"ESModeDefault": {
				"int": "1"
			},
			"ESOccupantCommand": {
				"int": "1"
			},
			"ESEncryptPDF": {
				"int": "1"
			},
			"ESQuietModeType": {
				"int": "0"
			},
			"ESReduceBlurColor": {
				"int": "1"
			},
			"ESDisplayKSize": {
				"int": "1"
			},
			"ESDisplayFolioSize": {
				"int": "1"
			},
			"ESDisplayOficioSize": {
				"int": "1"
			},
			"ESDisplayIndianLegalSize": {
				"int": "1"
			},
			"ESDisplayExecutiveSize": {
				"int": "1"
			},
			"ESColorEnhance": {
				"int": "2"
			},
			"ESEdgeFillLevelTop": {
				"float": "3"
			},
			"ESEdgeFillLevelBottom": {
				"float": "3"
			},
			"ESEdgeFillLevelLeft": {
				"float": "3"
			},
			"ESEdgeFillLevelRight": {
				"float": "3"
			},
			"ESDefaultScanMode": {
				"int": "0"
			},
			"ESGamma": {
				"float": "2.2"
			},
			"ESVenderID": {
				"string": "04B8"
			},
			"ESProductID": {
				"string": "11AE"
			},
			"ESImageClearNotSupport": {
				"int": "0"
			},
			"ESTextEnhancementNotSupport": {
				"int": "0"
			},
			"ESResolutionLimit": {
				"int": "0"
			},
			"ESIconFileName": {
				"string": "Printer_C365"
			},
			"ESVenderName": {
				"string": "EPSON"
			},
			"ESADFPixel": [
				{
					"Main": {
						"int": "0"
					},
					"Sub": {
						"int": "0"
					}
				}
			],
			"ESProductName": {
				"array_str": [
					"PID 11AE"
				]
			},
			"ESDeviceID": {
				"array_str": [
					"7fda086c0268dd4864ac25153da81b411203725d",
					"90fb3d1bae404cc52bb73a66673ffcc4e09ddeea",
					"c7cfa3626d07354661a164c40a17d89e103ca5bf"
				]
			},
			"ESProfileName": [
				{
					"Reflective": {
						"string": "WF2950_R.icc"
					}
				}
			],
			"ESResolution": [
				{
					"Min": {
						"int": "50"
					},
					"Max": {
						"int": "4800"
					},
					"Reflection": {
						"int": "1200"
					},
					"Moire": {
						"int": "600"
					}
				}
			],
			"ESImageFilterName": {
				"string": "EsImfl.dll"
			},
			"ESDDCName": {
				"string": "EsDDC.dll"
			},
			"ESDDEName": {
				"string": "EsDDE.dll"
			},
			"ESDDEADF": {
				"int": "18"
			},
			"ESDDEFlatbed": {
				"int": "18"
			},
			"ESFITName": {
				"string": "EsFit.dll"
			},
			"ESDTRName": {
				"string": "EsDTR2.dll"
			},
			"ESPDFLibName": {
				"string": "PDFLib.dll"
			},
			"ESPDFExtentionName": {
				"string": "espdfenc.dll"
			},
			"ESOCRName": {
				"string": "ocrsys.dll"
			},
			"ESAODName": {
				"string": "esaod.dll"
			}
		}
	],
	"TableInfo": [
		{
			"Profile": {
				"array_str": [
					"ESProfile0087"
				]
			},
			"GrayBalanceGamma": {
				"array_str": [
					"ESProfile1062"
				]
			},
			"USMOperation": {
				"array_str": [
					"ESUSM0008"
				]
			},
			"ClipConst": {
				"array_str": [
					"ESClipConst0001"
				]
			},
			"ClipCorrect": {
				"array_str": [
					"ESClipCorrect0000"
				]
			},
			"ClipRevise": {
				"array_str": [
					"ESClipRevise0005"
				]
			},
			"Moire": {
				"array_str": [
					"ESMoire2004",
					"ESMoire2005",
					"ESMoire2006"
				]
			},
			"Resolution": {
				"array_str": [
					"ESResolution0000",
					"ESResolution0019",
					"ESResolution0020"
				]
			},
			"MaxResolution": {
				"array_str": [
					"ESMaxResolution0000"
				]
			},
			"USMNoise": {
				"array_str": [
					"ESUSMNoise0002"
				]
			},
			"USMBlur": {
				"array_str": [
					"ESUSMBlur0000"
				]
			},
			"PreviewBW": {
				"array_str": [
					"ESPreviewBW0002"
				]
			},
			"FilterSequence": {
				"array_str": [
					"ESFilterSequence0000",
					"ESFilterSequence0002",
					"ESFilterSequence0004",
					"ESFilterSequence0006",
					"ESFilterSequence0101"
				]
			},
			"DefaultLUT": {
				"array_str": [
					"ESLUT0001",
					"ESLUT0002",
					"ESLUT0014"
				]
			}
		}
	],
	"__version": [
		{
			"Data Version": {
				"string": "1.00"
			},
			"Format Version": {
				"string": "1.00"
			}
		}
	]
}
