{
	"Profile": [
		{
			"Reflective": [
				{
					"R": {
						"array": [
							"10999",
							"-425",
							"-574"
						]
					},
					"G": {
						"array": [
							"-806",
							"10835",
							"-28"
						]
					},
					"B": {
						"array": [
							"57",
							"-2924",
							"12866"
						]
					}
				}
			],
			"Positive": [
				{
					"R": {
						"array": [
							"10999",
							"-425",
							"-574"
						]
					},
					"G": {
						"array": [
							"-806",
							"10835",
							"-28"
						]
					},
					"B": {
						"array": [
							"57",
							"-2924",
							"12866"
						]
					}
				}
			],
			"Negative": [
				{
					"R": {
						"array": [
							"10999",
							"-425",
							"-574"
						]
					},
					"G": {
						"array": [
							"-806",
							"10835",
							"-28"
						]
					},
					"B": {
						"array": [
							"57",
							"-2924",
							"12866"
						]
					}
				}
			]
		}
	],
	"__version": [
		{
			"Data Version": {
				"string": "1.00"
			},
			"Format Version": {
				"string": "1.00"
			}
		}
	]
}
